{
  "formatVersion": 1,
  "database": {
    "version": 1,
    "identityHash": "a2a6a2ae1d446ed1fb32d940a44214bc",
    "entities": [
      {
        "tableName": "timetables",
        "createSql": "CREATE TABLE IF NOT EXISTS `${TABLE_NAME}` (`url` TEXT NOT NULL, `timetableJson` TEXT NOT NULL, `nickname` TEXT, `lastChange` INTEGER NOT NULL, `lastCheck` INTEGER NOT NULL, PRIMARY KEY(`url`))",
        "fields": [
          {
            "fieldPath": "url",
            "columnName": "url",
            "affinity": "TEXT",
            "notNull": true
          },
          {
            "fieldPath": "json",
            "columnName": "timetableJson",
            "affinity": "TEXT",
            "notNull": true
          },
          {
            "fieldPath": "nickname",
            "columnName": "nickname",
            "affinity": "TEXT"
          },
          {
            "fieldPath": "lastChange",
            "columnName": "lastChange",
            "affinity": "INTEGER",
            "notNull": true
          },
          {
            "fieldPath": "lastCheck",
            "columnName": "lastCheck",
            "affinity": "INTEGER",
            "notNull": true
          }
        ],
        "primaryKey": {
          "autoGenerate": false,
          "columnNames": [
            "url"
          ]
        }
      },
      {
        "tableName": "config",
        "createSql": "CREATE TABLE IF NOT EXISTS `${TABLE_NAME}` (`id` INTEGER PRIMARY KEY AUTOINCREMENT NOT NULL, `setupCompleted` INTEGER NOT NULL DEFAULT false, `primaryTimetableId` TEXT)",
        "fields": [
          {
            "fieldPath": "id",
            "columnName": "id",
            "affinity": "INTEGER",
            "notNull": true
          },
          {
            "fieldPath": "setupCompleted",
            "columnName": "setupCompleted",
            "affinity": "INTEGER",
            "notNull": true,
            "defaultValue": "false"
          },
          {
            "fieldPath": "primaryTimetableId",
            "columnName": "primaryTimetableId",
            "affinity": "TEXT"
          }
        ],
        "primaryKey": {
          "autoGenerate": true,
          "columnNames": [
            "id"
          ]
        }
      }
    ],
    "setupQueries": [
      "CREATE TABLE IF NOT EXISTS room_master_table (id INTEGER PRIMARY KEY,identity_hash TEXT)",
      "INSERT OR REPLACE INTO room_master_table (id,identity_hash) VALUES(42, 'a2a6a2ae1d446ed1fb32d940a44214bc')"
    ]
  }
}